[
   {
       "season": 1,
       "chapter": 1,
       "seasonInChapter": 1,
       "displayName": "Chapter 1, Season 1",
       "startDate": "2017-10-24T09:00:00.000Z",
       "endDate": "2017-12-14T08:59:59.000Z"
   },
   {
       "season": 2,
       "chapter": 1,
       "seasonInChapter": 2,
       "displayName": "Chapter 1, Season 2",
       "startDate": "2017-12-14T09:00:00.000Z",
       "endDate": "2018-02-22T08:59:59.000Z"
   },
   {
       "season": 3,
       "chapter": 1,
       "seasonInChapter": 3,
       "displayName": "Chapter 1, Season 3",
       "startDate": "2018-02-22T09:00:00.000Z",
       "endDate": "2018-05-01T08:59:59.000Z"
   },
   {
       "season": 4,
       "chapter": 1,
       "seasonInChapter": 4,
       "displayName": "Chapter 1, Season 4",
       "startDate": "2018-05-01T09:00:00.000Z",
       "endDate": "2018-07-11T08:59:59.000Z"
   },
   {
       "season": 5,
       "chapter": 1,
       "seasonInChapter": 5,
       "displayName": "Chapter 1, Season 5",
       "startDate": "2018-07-11T09:00:00.000Z",
       "endDate": "2018-09-27T08:59:59.000Z"
   },
   {
       "season": 6,
       "chapter": 1,
       "seasonInChapter": 6,
       "displayName": "Chapter 1, Season 6",
       "startDate": "2018-09-27T09:00:00.000Z",
       "endDate": "2018-12-06T08:59:59.000Z"
   },
   {
       "season": 7,
       "chapter": 1,
       "seasonInChapter": 7,
       "displayName": "Chapter 1, Season 7",
       "startDate": "2018-12-06T09:00:00.000Z",
       "endDate": "2019-02-28T07:59:59.000Z"
   },
   {
       "season": 8,
       "chapter": 1,
       "seasonInChapter": 8,
       "displayName": "Chapter 1, Season 8",
       "startDate": "2019-02-28T08:00:00.000Z",
       "endDate": "2019-05-09T07:59:59.000Z"
   },
   {
       "season": 9,
       "chapter": 1,
       "seasonInChapter": 9,
       "displayName": "Chapter 1, Season 9",
       "startDate": "2019-05-09T08:00:00.000Z",
       "endDate": "2019-08-01T07:59:59.000Z"
   },
   {
       "season": 10,
       "chapter": 1,
       "seasonInChapter": 10,
       "displayName": "Chapter 1, Season X",
       "startDate": "2019-08-01T08:00:00.000Z",
       "endDate": "2019-10-13T18:00:00.000Z"
   },
   {
       "season": 11,
       "chapter": 2,
       "seasonInChapter": 1,
       "displayName": "Chapter 2, Season 1",
       "startDate": "2019-10-15T08:00:00.000Z",
       "endDate": "2020-02-20T08:59:59.000Z"
   },
   {
       "season": 12,
       "chapter": 2,
       "seasonInChapter": 2,
       "displayName": "Chapter 2, Season 2",
       "startDate": "2020-02-20T09:00:00.000Z",
       "endDate": "2020-06-17T05:59:59.000Z"
   },
   {
       "season": 13,
       "chapter": 2,
       "seasonInChapter": 3,
       "displayName": "Chapter 2, Season 3",
       "startDate": "2020-06-17T06:00:00.000Z",
       "endDate": "2020-08-27T05:59:59.000Z"
   },
   {
       "season": 14,
       "chapter": 2,
       "seasonInChapter": 4,
       "displayName": "Chapter 2, Season 4",
       "startDate": "2020-08-27T06:00:00.000Z",
       "endDate": "2020-12-02T04:59:59.000Z"
   },
   {
       "season": 15,
       "chapter": 2,
       "seasonInChapter": 5,
       "displayName": "Chapter 2, Season 5",
       "startDate": "2020-12-02T05:00:00.000Z",
       "endDate": "2021-03-16T03:59:59.000Z"
   },
   {
       "season": 16,
       "chapter": 2,
       "seasonInChapter": 6,
       "displayName": "Chapter 2, Season 6",
       "startDate": "2021-03-16T04:00:00.000Z",
       "endDate": "2021-06-08T05:59:59.000Z"
   },
   {
       "season": 17,
       "chapter": 2,
       "seasonInChapter": 7,
       "displayName": "Chapter 2, Season 7",
       "startDate": "2021-06-08T06:00:00.000Z",
       "endDate": "2021-09-13T05:59:59.000Z"
   },
   {
       "season": 18,
       "chapter": 2,
       "seasonInChapter": 8,
       "displayName": "Chapter 2, Season 8",
       "startDate": "2021-09-13T06:00:00.000Z",
       "endDate": "2021-12-04T21:15:00.000Z"
   },
   {
       "season": 19,
       "chapter": 3,
       "seasonInChapter": 1,
       "displayName": "Chapter 3, Season 1",
       "startDate": "2021-12-05T15:00:00.000Z",
       "endDate": "2022-03-19T08:59:59.000Z"
   },
   {
       "season": 20,
       "chapter": 3,
       "seasonInChapter": 2,
       "displayName": "Chapter 3, Season 2",
       "startDate": "2022-03-19T09:00:00.000Z",
       "endDate": null
   }
]